mezzanine_seminars/__init__.py
mezzanine_seminars/apps.py
mezzanine_seminars/defaults.py
mezzanine_seminars/urls.py
mezzanine_seminars/views.py
mezzanine_seminars/admin/__init__.py
mezzanine_seminars/admin/seminars.py
mezzanine_seminars/admin/surveys.py
mezzanine_seminars/forms/__init__.py
mezzanine_seminars/forms/stripe.py
mezzanine_seminars/forms/surveys.py
mezzanine_seminars/migrations/0001_initial.py
mezzanine_seminars/migrations/0002_registration_codes.py
mezzanine_seminars/migrations/__init__.py
mezzanine_seminars/models/__init__.py
mezzanine_seminars/models/seminars.py
mezzanine_seminars/models/surveys.py
mezzanine_seminars/templates/admin/mezzanine_seminars/seminar/change_form.html
mezzanine_seminars/templates/seminars/registration_create.html
mezzanine_seminars/templates/seminars/seminar_detail.html
mezzanine_seminars/templates/seminars/seminar_list.html
mezzanine_seminars/templates/seminars/survey_response_create.html
mezzanine_seminars/templates/seminars/emails/registration_confirmation.html
mezzanine_seminars/templates/seminars/emails/registration_confirmation.txt
mezzanine_seminars-1.7.1.dist-info/LICENSE
mezzanine_seminars-1.7.1.dist-info/METADATA
mezzanine_seminars-1.7.1.dist-info/WHEEL
mezzanine_seminars-1.7.1.dist-info/top_level.txt
mezzanine_seminars-1.7.1.dist-info/RECORD
