Metadata-Version: 2.1
Name: mezzanine-seminars
Version: 1.7.1
Summary: Seminar platform for Mezzanine CMS
Home-page: http://github.com/unplugstudio/mezzanine-seminars
Author: Unplug Studio
Author-email: developers@unplug.studio
License: UNKNOWN
Platform: UNKNOWN
Classifier: Programming Language :: Python
Classifier: Programming Language :: Python :: 2
Classifier: Programming Language :: Python :: 2.7
Classifier: Programming Language :: Python :: 3
Classifier: Programming Language :: Python :: 3.6
Classifier: Programming Language :: Python :: 3.7
Classifier: Programming Language :: Python :: 3.8
Requires-Python: !=3.0,!=3.1,!=3.2,!=3.3,!=3.4,!=3.5,>=2.7
Requires-Dist: django (<2.0,>=1.8)
Requires-Dist: django-contrib-comments (==1.8)
Requires-Dist: mezzanine (<5,>=4)
Requires-Dist: mezzy (<3,>=2.4)
Requires-Dist: unicodecsv
Provides-Extra: stripe
Requires-Dist: stripe (<3,>=2.48) ; extra == 'stripe'
Provides-Extra: testing
Requires-Dist: django-dynamic-fixture (<4,>=3) ; extra == 'testing'
Requires-Dist: django-functest (<2,>=1) ; extra == 'testing'
Requires-Dist: mock ; extra == 'testing'
Requires-Dist: pathlib2 ; extra == 'testing'
Requires-Dist: pytest-django (<4,>=3) ; extra == 'testing'
